{"version":"0.4","title":"Contact Us 4 *","type":"page","content":[{"id":"4bb601b5","settings":{"layout":"full_width","gap":"no"},"elements":[{"id":"5d9639cd","settings":{"_column_size":100,"_inline_size":null},"elements":[{"id":"1dd7ac5f","settings":{"bwcolor":"true","locations":[{"lat":"51.5007046","lon":"-0.12457480000000487","title":"Big Ben","_id":"bm36e5t","content":""},{"lat":"48.8582285","lon":"2.2943877000000157","title":"Eifel Tower","content":"Location description for Eifel Tower","_id":"cqcyj1s"},{"lat":"43.722952","lon":"10.396596999999929","title":"Leaning Tower of Pisa","content":"Location description for Pisa Tower","_id":"kv77i0z"}]},"elements":[],"isInner":false,"widgetType":"rt-google-maps","elType":"widget"}],"isInner":false,"elType":"column"}],"isInner":false,"elType":"section"},{"id":"37cf8595","settings":{"content_width":{"unit":"px","size":1280},"gap":"wider","structure":"30","padding":{"unit":"px","top":"40","right":"0","bottom":"40","left":"0","isLinked":false}},"elements":[{"id":"5ec2f2f7","settings":{"_column_size":33,"_inline_size":null,"_inline_size_tablet":100,"padding":{"unit":"px","top":"0","right":"30","bottom":"30","left":"30","isLinked":false},"border_border":"solid","rt-border":{"unit":"px","top":"0","right":"1","bottom":"0","left":"0","isLinked":false},"rt-border_tablet":{"unit":"px","top":"0","right":"0","bottom":"0","left":"0","isLinked":false}},"elements":[{"id":"65dc2221","settings":{"heading_text":"New York","size":"H5","style":"style-6","_margin":{"unit":"px","top":"0","right":"0","bottom":"40","left":"0","isLinked":false}},"elements":[],"isInner":false,"widgetType":"rt-heading","elType":"widget"},{"id":"6499f5cb","settings":{"icon_list":[{"text":"63739 street lorem ipsum dolor City, Country","icon":"rt-elementor-icon icon-basic_geolocalize","_id":"vy70ki2","link":{"url":"","is_external":"","nofollow":""}},{"text":"+1 123 312 32 23","icon":"rt-elementor-icon icon-basic-smartphone","_id":"sexg4my","link":{"url":"","is_external":"","nofollow":""}},{"text":"support@company.com","icon":"rt-elementor-icon icon-basic-support","_id":"wb35idb","link":{"url":"","is_external":"","nofollow":""}},{"text":"info@company.com","icon":"rt-elementor-icon icon-basic-mail","_id":"eztcko7","link":{"url":"","is_external":"","nofollow":""}}],"space_between":{"unit":"px","size":20},"rt_icon_padding":{"unit":"px","top":"0","right":"0","bottom":"0","left":"0","isLinked":false},"text_indent":{"unit":"px","size":20},"icon_size":{"unit":"px","size":40},"text_color":"#000000"},"elements":[],"isInner":false,"widgetType":"icon-list","elType":"widget"}],"isInner":false,"elType":"column"},{"id":"15f0743a","settings":{"_column_size":33,"_inline_size":null,"_inline_size_tablet":100,"padding":{"unit":"px","top":"0","right":"30","bottom":"30","left":"30","isLinked":false},"border_border":"solid","rt-border":{"unit":"px","top":"0","right":"1","bottom":"0","left":"0","isLinked":false},"rt-border_tablet":{"unit":"px","top":"0","right":"0","bottom":"0","left":"0","isLinked":false}},"elements":[{"id":"4343580a","settings":{"heading_text":"London","size":"H5","style":"style-6","_margin":{"unit":"px","top":"0","right":"0","bottom":"40","left":"0","isLinked":false}},"elements":[],"isInner":false,"widgetType":"rt-heading","elType":"widget"},{"id":"145bf87","settings":{"icon_list":[{"text":"63739 street lorem ipsum dolor City, Country","icon":"rt-elementor-icon icon-basic_geolocalize","_id":"vy70ki2","link":{"url":"","is_external":"","nofollow":""}},{"text":"+1 123 312 32 23","icon":"rt-elementor-icon icon-basic-smartphone","_id":"sexg4my","link":{"url":"","is_external":"","nofollow":""}},{"text":"support@company.com","icon":"rt-elementor-icon icon-basic-support","_id":"wb35idb","link":{"url":"","is_external":"","nofollow":""}},{"text":"info@company.com","icon":"rt-elementor-icon icon-basic-mail","_id":"eztcko7","link":{"url":"","is_external":"","nofollow":""}}],"space_between":{"unit":"px","size":20},"rt_icon_padding":{"unit":"px","top":"0","right":"0","bottom":"0","left":"0","isLinked":false},"text_indent":{"unit":"px","size":20},"icon_size":{"unit":"px","size":40},"text_color":"#000000"},"elements":[],"isInner":false,"widgetType":"icon-list","elType":"widget"}],"isInner":false,"elType":"column"},{"id":"b4811ed","settings":{"_column_size":33,"_inline_size":null,"_inline_size_tablet":100,"padding":{"unit":"px","top":"0","right":"30","bottom":"30","left":"30","isLinked":false}},"elements":[{"id":"6380f259","settings":{"heading_text":"Berlin","size":"H5","style":"style-6","_margin":{"unit":"px","top":"0","right":"0","bottom":"40","left":"0","isLinked":false}},"elements":[],"isInner":false,"widgetType":"rt-heading","elType":"widget"},{"id":"73dd1afc","settings":{"icon_list":[{"text":"63739 street lorem ipsum dolor City, Country","icon":"rt-elementor-icon icon-basic_geolocalize","_id":"vy70ki2","link":{"url":"","is_external":"","nofollow":""}},{"text":"+1 123 312 32 23","icon":"rt-elementor-icon icon-basic-smartphone","_id":"sexg4my","link":{"url":"","is_external":"","nofollow":""}},{"text":"support@company.com","icon":"rt-elementor-icon icon-basic-support","_id":"wb35idb","link":{"url":"","is_external":"","nofollow":""}},{"text":"info@company.com","icon":"rt-elementor-icon icon-basic-mail","_id":"eztcko7","link":{"url":"","is_external":"","nofollow":""}}],"space_between":{"unit":"px","size":20},"rt_icon_padding":{"unit":"px","top":"0","right":"0","bottom":"0","left":"0","isLinked":false},"text_indent":{"unit":"px","size":20},"icon_size":{"unit":"px","size":40},"text_color":"#000000"},"elements":[],"isInner":false,"widgetType":"icon-list","elType":"widget"}],"isInner":false,"elType":"column"}],"isInner":false,"elType":"section"},{"id":"b6295eb","settings":{"content_width":{"unit":"px","size":1220},"margin":{"unit":"px","top":"20","right":0,"bottom":"100","left":0,"isLinked":false}},"elements":[{"id":"7990897","settings":{"_column_size":100,"_inline_size":null,"background_background":"classic","background_color":"#fbfbfb","border_border":"solid","border_width":{"unit":"px","top":"2","right":"2","bottom":"2","left":"2","isLinked":true},"padding":{"unit":"px","top":"60","right":"60","bottom":"60","left":"60","isLinked":true},"padding_mobile":{"unit":"px","top":"20","right":"20","bottom":"20","left":"20","isLinked":true}},"elements":[{"id":"4ea38e4f","settings":{"heading_text":"Contact Form","size":"H5","icon_name":"rt-elementor-icon icon-basic-mail-open-text","icon_size_elementor":{"unit":"px","size":40},"_margin":{"unit":"px","top":"0","right":"0","bottom":"50","left":"0","isLinked":false}},"elements":[],"isInner":false,"widgetType":"rt-heading","elType":"widget"},{"id":"33cc341","settings":{"email":"info@company.com"},"elements":[],"isInner":false,"widgetType":"rt-contact-form","elType":"widget"}],"isInner":false,"elType":"column"}],"isInner":false,"elType":"section"}]}